{
  "$schema": "https://schemas.premid.app/metadata/1.13",
  "apiVersion": 1,
  "author": {
    "name": "EGGSY",
    "id": "162969778699501569"
  },
  "service": "GAİN",
  "description": {
    "en": "GAİN offers long, short series as well as creative movies, latest news, documentaries and much more!",
    "tr": "GAİN ile uzun, kısa diziler, filmler, yaratıcı, güncel içerikler, belgeseller, spor, eğlence programları ve dahası istediğiniz her zaman, her yerde sizinle!"
  },
  "url": "gain.tv",
  "version": "1.0.19",
  "logo": "https://cdn.rcd.gg/PreMiD/websites/G/GA%C4%B0N/assets/logo.jpeg",
  "thumbnail": "https://cdn.rcd.gg/PreMiD/websites/G/GA%C4%B0N/assets/thumbnail.jpeg",
  "color": "#f5313f",
  "category": "videos",
  "tags": [
    "turkish",
    "series",
    "movie"
  ],
  "settings": [
    {
      "id": "showImages",
      "title": "İçerik Resimleri",
      "icon": "fas fa-images",
      "value": true
    },
    {
      "id": "showButtons",
      "title": "Butonları Göster",
      "icon": "fas fa-mouse",
      "value": true
    }
  ]
}
