{
  "$schema": "https://schemas.premid.app/metadata/1.5",
  "author": {
    "name": "Bas950",
    "id": "241278257335500811"
  },
  "contributors": [
    {
      "name": "Itz_Hoffe",
      "id": "175324549263523840"
    }
  ],
  "service": "LabyMod",
  "description": {
    "en": "An all in one Minecraft PvP Modification to increase your ingame experience.",
    "nl": "Een alles-in-één Minecraft PvP modificatie om uw ingame-ervaring te verbeteren."
  },
  "url": "www.labymod.net",
  "version": "1.2.9",
  "logo": "https://i.imgur.com/PHdC5bf.png",
  "thumbnail": "https://i.imgur.com/SDMxfEg.png",
  "color": "#008fe8",
  "tags": [
    "minecraft",
    "labymod"
  ],
  "category": "games",
  "regExp": "([a-z0-9-]+[.])*labymod[.]net[/]"
}