{
	"$schema": "https://schemas.premid.app/metadata/1.11",
	"apiVersion": 1,
	"author": {
		"name": "Kazo",
		"id": "393071912189952011"
	},
	"service": "Riot Games",
	"description": {
		"en": "The Presence for *all* websites related to Riot Games!",
		"de": "Die Presence für *alle* Webseiten die von Riot Games sind!",
		"nl": "De aanwezigheid voor *alle* websites gerelateerd aan Riot Games!"
	},
	"url": [
		"riotgames.com",
		"leagueoflegends.com",
		"playruneterra.com",
		"playvalorant.com"
	],
	"regExp": "([a-z0-9-]+[.])*(riotgames|leagueoflegends|playruneterra|playvalorant)[.]com[/]",
	"version": "1.0.20",
	"logo": "https://cdn.rcd.gg/PreMiD/websites/R/Riot%20Games/assets/logo.png",
	"thumbnail": "https://cdn.rcd.gg/PreMiD/websites/R/Riot%20Games/assets/thumbnail.jpg",
	"color": "#d13639",
	"category": "games",
	"tags": [
		"lol",
		"leagueoflegends",
		"esport",
		"riot",
		"riotgames",
		"valorant",
		"legendsofruneterra",
		"teamfighttactics",
		"leagueoflegendswildrift"
	]
}