{
  "IGDB.discover": {
    "description": "Explore the game database.",
    "message": "Browsing games"
  },
  "IGDB.comingSoon": {
    "description": "View upcoming game releases.",
    "message": "Viewing future games"
  },
  "IGDB.recentlyReleased": {
    "description": "View recently released games.",
    "message": "Viewing recently released games"
  },
  "IGDB.newGame": {
    "description": "Add a new game.",
    "message": "Adding a new game"
  },
  "IGDB.newCompany": {
    "description": "Add a new company.",
    "message": "Adding a new company"
  },
  "IGDB.browseGenres": {
    "description": "Browse different game genres.",
    "message": "Browsing genres"
  },
  "IGDB.browsePlatforms": {
    "description": "Browse different gaming platforms.",
    "message": "Browsing platforms"
  },
  "IGDB.viewPlatform": {
    "description": "View details of a specific platform.",
    "message": "Viewing platform:"
  },
  "IGDB.top100": {
    "description": "View the Top 100 games.",
    "message": "Viewing Top 100"
  },
  "IGDB.reviews": {
    "description": "Find game reviews.",
    "message": "Finding game reviews"
  },
  "IGDB.browseThemes": {
    "description": "Browse game themes.",
    "message": "Browsing themes"
  },
  "IGDB.viewTheme": {
    "description": "View games under a specific theme.",
    "message": "Viewing theme:"
  },
  "IGDB.browseCollections": {
    "description": "Browse game collections.",
    "message": "Browsing collections"
  },
  "IGDB.viewCollection": {
    "description": "View details of a specific collection.",
    "message": "Viewing collection:"
  },
  "IGDB.browsePlayerPerspectives": {
    "description": "Browse different player perspectives.",
    "message": "Browsing player perspectives"
  },
  "IGDB.viewPlayerPerspectives": {
    "description": "View games from a specific player perspective.",
    "message": "Viewing player perspective's games:"
  },
  "IGDB.browseCharacters": {
    "description": "Browse game characters.",
    "message": "Browsing characters"
  },
  "IGDB.viewCharacter": {
    "description": "View details of a specific character.",
    "message": "Viewing character:"
  },
  "IGDB.browseEvents": {
    "description": "Browse events in the gaming world.",
    "message": "Browsing events"
  },
  "IGDB.viewEvent": {
    "description": "View details of a specific event.",
    "message": "Viewing event:"
  },
  "IGDB.browseFranchises": {
    "description": "Browse game franchises.",
    "message": "Browsing franchises"
  },
  "IGDB.viewFranchises": {
    "description": "View details of a specific franchise.",
    "message": "Viewing franchise:"
  },
  "IGDB.browseCategories": {
    "description": "Browse game categories.",
    "message": "Browsing categories"
  },
  "IGDB.browseCompanies": {
    "description": "Browse gaming companies.",
    "message": "Browsing companies"
  },
  "IGDB.viewCompany": {
    "description": "View details of a specific company.",
    "message": "Viewing company:"
  },
  "IGDB.browseGameEngines": {
    "description": "Browse game engines used in development.",
    "message": "Browsing game engines"
  },
  "IGDB.viewGameEngine": {
    "description": "View details of a specific game engine.",
    "message": "Viewing game engine:"
  },
  "IGDB.settings": {
    "description": "Access IGDB account settings.",
    "message": "Viewing Settings"
  },
  "IGDB.karmaHunters": {
    "description": "View details about Karma Hunters.",
    "message": "Viewing Karma Hunters"
  },
  "IGDB.about": {
    "description": "Learn more about IGDB.",
    "message": "Viewing About"
  },
  "IGDB.contact": {
    "description": "View IGDB contact information.",
    "message": "Viewing Contact"
  },
  "IGDB.API": {
    "description": "Explore the IGDB API.",
    "message": "Viewing API"
  }
}
