{
	"$schema": "https://schemas.premid.app/metadata/1.7",
	"author": {
		"name": "sylvesteryue",
		"id": "246138990674051073"
	},
	"service": "binarysearch",
	"description": {
		"en": "binarysearch is a free site where one can work on coding and algorithms problems with friends.",
		"nl": "binarysearch is een gratis site waar men met vrienden kan werken aan coderings- en algoritmeproblemen.",
		"vi_VN": "binarysearch là trang web miễn phí nơi mọi người có thể giải các vấn đề lập trình và thuật toán cùng bạn bè."
	},
	"url": [
		"binarysearch.com",
		"www.binarysearch.com"
	],
	"version": "1.0.13",
	"logo": "https://i.imgur.com/0HotbTy.png",
	"thumbnail": "https://i.imgur.com/Q59B8YD.png",
	"color": "#384252",
	"category": "other",
	"tags": [
		"technology",
		"programming",
		"coding",
		"education",
		"developer"
	]
}