{
  "author": {
    "name": "MertBhey",
    "id": "623932457401450496"
  },
  "service": "Simsek Bot",
  "description": {
    "tr": "Simsek Bot - Bir 'Premium' bottan daha fazlası...",
    "en": "Simsek Bot - Better than a 'Premium' bot..."
  },
  "url": ["www.simsekbot.com","simsekbot.com","istatistik.simsekbot.com"],
  "version": "1.0.0",
  "logo": "https://i.imgur.com/3SBvg40.png",
  "thumbnail": "https://i.imgur.com/3SBvg40.png",
  "color": "#a50101",
  "tags": ["bot", "simsek", "simsekbot", "turkish"],
  "category": "other"
}
