{
    "$schema": "https://schemas.premid.app/metadata/1.4",
    "service": "CodeChef",
    "author": {
      "name": "Palskie",
      "id": "90431685472038912"
    },
    "category": "other",
    "logo": "https://i.imgur.com/E5jTqq0.png",
    "thumbnail": "https://i.imgur.com/ZsRfm2Q.png",
    "version": "1.0.1",
    "color": "#e1d5d5",
    "tags": [
      "coding",
      "programming",
      "educational",
      "competition"
    ],
    "url": [
      "www.codechef.com",
      "blog.codechef.com",
      "discuss.codechef.com"
    ],
    "description": {
      "en": "CodeChef is a competitive programming community of programmers from across the globe."
    }
  }