{
  "author": {
    "name": "Kozou",
    "id": "379362415428632576"
  },
  "service": "Topachat",
  "description": {
    "en": "Top Achat is a retail chain of computer and electronic products for the general public carrying out its activities exclusively on the Web.",
    "fr": "Top Achat est une enseigne de distribution de produits informatiques et électroniques grand public exerçant ses activités uniquement sur le Web."
  },
  "url": ["www.topachat.com",
          "secure.topachat.com"],
  "version": "1.0.0",
  "logo": "https://i.imgur.com/znJjvom.png",
  "thumbnail": "https://i.imgur.com/hEqPcXI.png",
  "color": "#0275b4",
  "tags": [
    "topachat",
    "computer",
    "french",
    "hardware"
  ],
  "category": "other"
}