{
	"$schema": "https://schemas.premid.app/metadata/1.11",
	"apiVersion": 1,
	"author": {
		"name": "Drakonir",
		"id": "469868455902969866"
	},
	"service": "AnimeTube",
	"description": {
		"de": "Die Anime Community mit hunderten Anime als Livestream.",
		"en": "The Anime Community with hundreds of Anime livestreams.",
		"nl": "De Anime community met honderden Anime livestreams.",
		"vi_VN": "Cộng đồng Anime với hàng trăm bản Anime được phát trực tuyến."
	},
	"url": "anime-tube.tv",
	"version": "1.0.23",
	"logo": "https://cdn.rcd.gg/PreMiD/websites/A/AnimeTube/assets/logo.png",
	"thumbnail": "https://cdn.rcd.gg/PreMiD/websites/A/AnimeTube/assets/thumbnail.png",
	"color": "#9b403f",
	"category": "anime",
	"tags": [
		"anime"
	],
	"iframe": true,
	"iFrameRegExp": ".*"
}