{
	"$schema": "https://schemas.premid.app/metadata/1.11",
	"apiVersion": 1,
	"author": {
		"name": "gausie",
		"id": "263438077865754644"
	},
	"service": "Kingdom of Loathing",
	"altnames": [
		"KoL",
		"KoLmafia"
	],
	"description": {
		"en": "Kingdom of Loathing (abbreviated KoL) is a browser-based multiplayer role-playing game designed and operated by Asymmetric Publications",
		"nl": "Kingdom of Loathing (afgekort KoL) is een browsergebaseerd rollenspel voor meerdere spelers, ontworpen en beheerd door Asymmetric Publications"
	},
	"url": "kingdomofloathing.com",
	"regExp": "([a-z0-9]+\\.)*kingdomofloathing.com|(127\\.0\\.0\\.1|localhost):6008\\d",
	"version": "1.0.18",
	"logo": "https://cdn.rcd.gg/PreMiD/websites/K/Kingdom%20of%20Loathing/assets/logo.png",
	"thumbnail": "https://cdn.rcd.gg/PreMiD/websites/K/Kingdom%20of%20Loathing/assets/thumbnail.png",
	"color": "#0000ff",
	"category": "games",
	"tags": [
		"rpg",
		"asym",
		"kol"
	],
	"iframe": true,
	"iFrameRegExp": ".*?\\.php"
}