{
	"$schema": "https://schemas.premid.app/metadata/1.7",
	"author": {
		"name": "erdem",
		"id": "292692556809109534"
	},
	"service": "Sürat Kargo",
	"description": {
		"en": "Sürat Kargo, delivery company providing services in Turkey.",
		"tr": "Sürat Kargo, Türkiye'de hizmet veren bir kargo şirketi",
		"nl": "Sürat Kargo, koeriersbedrijf dat diensten verleent in Turkije."
	},
	"url": [
		"suratkargo.com.tr",
		"www.suratkargo.com.tr"
	],
	"version": "1.0.11",
	"logo": "https://i.imgur.com/CBsEtCf.png",
	"thumbnail": "https://i.imgur.com/B7H16MR.png",
	"color": "#e33d2f",
	"category": "other",
	"tags": [
		"surat",
		"delivery",
		"shipping",
		"turkish",
		"turkey"
	]
}