{
  "$schema": "https://schemas.premid.app/metadata/1.0",
  "author": {
    "name": "Dark_Ville",
    "id": "638080361179512853"
  },
  "url": [
    "www.mediafire.com",
    "mediafire.zendesk.com",
    "app.mediafire.com",
    "blog.mediafire.com"
  ],
  "description": {
    "en": "File sharing and storage made simple",
    "nl": "Bestanden delen en opslag is simpel gemaakt"
  },
  "service": "Mediafire",
  "version": "1.0.1",
  "logo": "https://i.imgur.com/nIZ0XtN.png",
  "thumbnail": "https://i.imgur.com/DwfSIyG.jpg",
  "color": "#FF0000",
  "tags": [
    "mediafire",
    "media",
    "fire",
    "download",
    "storage"
  ],
  "category": "other"
}