{
  "$schema": "https://schemas.premid.app/metadata/1.0",
  "author": {
    "name": "MrBartusek",
    "id": "212988300137463809"
  },
  "service": "Unsplash",
  "description": {
    "en": "Beautiful, free images and photos that you can download and use for any project. Better than any royalty free or stock photos.",
    "nl": "Mooie, gratis afbeeldingen en foto's die u kunt downloaden en voor elk project kunt gebruiken. Beter dan alle royaltyvrije foto's of stockfoto's."
  },
  "url": "unsplash.com",
  "version": "1.0.3",
  "logo": "https://i.imgur.com/1fqpSA1.png",
  "thumbnail": "https://i.imgur.com/75wDPD4.jpg",
  "color": "#ffffff",
  "tags": [
    "images",
    "photos"
  ],
  "category": "other"
}