{
  "$schema": "https://schemas.premid.app/metadata/1.0",
  "author": {
    "name": "N0chteil ^^",
    "id": "495901098926669825"
  },
  "service": "RealLifeGTAV",
  "description": {
    "en": "Real Life GTAV is a german FiveM roleplay server with custom scripts and more!",
    "de": "Real Life GTAV ist ein deutscher FiveM Roleplay Server mit eigenen Scripts und mehr!"
  },
  "url": [
    "reallifegtav.de",
    "rlv.link",
    "forum.reallifegtav.de",
    "forum.rlv.link"
  ],
  "version": "2.1.0",
  "logo": "https://i.imgur.com/FDkOoBd.png",
  "thumbnail": "https://i.imgur.com/QjWhm3D.png",
  "color": "#000",
  "tags": [
    "fivem",
    "reallifegtav",
    "gtav"
  ],
  "category": "games",
  "settings": [
    {
      "id": "showUsername",
      "title": "Nutzername einblenden",
      "icon": "fas fa-signature",
      "value": true
    },
    {
      "id": "timeElapsed",
      "title": "Timestamp einblenden",
      "icon": "fad fa-hourglass-half",
      "value": true
    },
    {
      "id": "showButtons",
      "title": "Buttons anzeigen",
      "icon": "fad fa-mouse-pointer",
      "value": true
    }
  ]
}
