{
	"$schema": "https://schemas.premid.app/metadata/1.11",
	"apiVersion": 1,
	"author": {
		"name": "Striker",
		"id": "215509157837537280"
	},
	"service": "CoolMathGames",
	"description": {
		"en": "Coolmath Games is a brain-training site, for everyone, where logic & thinking & math meets fun & games.",
		"nl": "Coolmath Games is een hersentrainingssite, voor iedereen, waar logica & denken & rekenen samenkomen met plezier & games.",
		"vi_VN": "CoolMathGames là trang luyện trí óc, dành cho tất cả mọi người, nơi logic & suy nghĩ & toán gặp gỡ trò chơi & vui nhộn."
	},
	"url": [
		"www.coolmathgames.com",
		"coolmathgames.com"
	],
	"version": "1.2.27",
	"logo": "https://cdn.rcd.gg/PreMiD/websites/C/CoolMathGames/assets/logo.png",
	"thumbnail": "https://cdn.rcd.gg/PreMiD/websites/C/CoolMathGames/assets/thumbnail.png",
	"color": "#3DB5F9",
	"category": "games",
	"tags": [
		"entertainment",
		"fun"
	]
}