{
	"$schema": "https://schemas.premid.app/metadata/1.11",
	"apiVersion": 1,
	"author": {
		"name": "Snazzah",
		"id": "158049329150427136"
	},
	"service": "Gitbook",
	"description": {
		"en": "Share knowledge, boost your team's productivity and make your users happy.",
		"nl": "Deel kennis, verhoog de productiviteit van uw team en maak uw gebruikers blij."
	},
	"url": "app.gitbook.com",
	"regExp": "([a-z0-9-]+)[.]gitbook[.]io|app[.]gitbook[.]com",
	"version": "1.0.18",
	"logo": "https://cdn.rcd.gg/PreMiD/websites/G/Gitbook/assets/logo.png",
	"thumbnail": "https://cdn.rcd.gg/PreMiD/websites/G/Gitbook/assets/thumbnail.png",
	"color": "#3884FF",
	"category": "other",
	"tags": [
		"documentation",
		"collaboration"
	]
}