{
	"$schema": "https://schemas.premid.app/metadata/1.10",
	"author": {
		"name": "Dark_Ville",
		"id": "638080361179512853"
	},
	"contributors": [
		{
			"name": "Alexx",
			"id": "604182077088202784"
		},
		{
			"name": "Aidan",
			"id": "235532241403510795"
		}
	],
	"service": "SiriusXM",
	"description": {
		"en": "SiriusXM is like nothing you've ever heard before — it's a whole new world of radio. Imagine channels and channels of anything you want to listen to.",
		"nl": "SiriusXM is iets wat je nog nooit gehoord hebt - het is een hele nieuwe wereld van radio. Stel je kanalen en kanalen voor van alles waar je naar wilt luisteren."
	},
	"url": [
		"can.siriusxm.com",
		"www.siriusxm.com"
	],
	"version": "2.0.0",
	"logo": "https://i.imgur.com/WVRaXaV.png",
	"thumbnail": "https://i.imgur.com/Z6R6cKO.png",
	"color": "#0081FF",
	"category": "music",
	"tags": [
		"music",
		"radio"
	]
}