{
	"$schema": "https://schemas.premid.app/metadata/1.10",
	"author": {
		"name": "Marino",
		"id": "598953747963707409"
	},
	"contributors": [
		{
			"name": "Dark_Ville",
			"id": "638080361179512853"
		}
	],
	"service": "Epic Games",
	"description": {
		"en": "Epic Games, Inc. is an American video game and software developer and publisher based in Cary, North Carolina.",
		"nl": "Epic Games, Inc. is een Amerikaanse ontwikkelaar en uitgever van videospelletjes en software, gevestigd in Cary, North Carolina."
	},
	"url": [
		"store.epicgames.com",
		"www.epicgames.com"
	],
	"version": "1.1.9",
	"logo": "https://cdn.rcd.gg/PreMiD/websites/E/Epic%20Games/assets/logo.png",
	"thumbnail": "https://cdn.rcd.gg/PreMiD/websites/E/Epic%20Games/assets/thumbnail.png",
	"color": "#2A2A2A",
	"category": "games",
	"tags": [
		"epic",
		"games",
		"game",
		"fortnite"
	],
	"settings": [
		{
			"id": "privacy",
			"title": "Privacy Mode",
			"icon": "fas fa-user-secret",
			"value": false
		},
		{
			"id": "buttons",
			"title": "Show Buttons",
			"icon": "fas fa-compress-arrows-alt",
			"value": true,
			"if": {
				"privacy": false
			}
		},
		{
			"id": "covers",
			"title": "Show Cover",
			"icon": "fad fa-images",
			"value": true,
			"if": {
				"privacy": false
			}
		}
	]
}