{
	"$schema": "https://schemas.premid.app/metadata/1.11",
	"apiVersion": 1,
	"author": {
		"name": "Mitchellonii",
		"id": "490664749315653642"
	},
	"contributors": [
		{
			"name": "Vukky",
			"id": "708333380525228082"
		}
	],
	"service": "Vukkybox",
	"description": {
		"en": "The online gachapon-like game that lets you collect mysterious creatures known as Vukkies!",
		"fi": "Gachapon tyylinen nettipeli, jossa keräät salaperäisiä olentoja, jotka tunnetaan Vukkyinä!",
		"no": "Et online gacha-spill som lar deg samle mystiske skapninger kjent som Vukkyer!"
	},
	"url": "vukkybox.com",
	"version": "1.1.17",
	"logo": "https://cdn.rcd.gg/PreMiD/websites/V/Vukkybox/assets/logo.png",
	"thumbnail": "https://cdn.rcd.gg/PreMiD/websites/V/Vukkybox/assets/thumbnail.png",
	"color": "#5ea1c0",
	"category": "games",
	"tags": [
		"gacha",
		"game",
		"vukky",
		"vukkybox",
		"box",
		"litdevs",
		"vukkies"
	]
}