{
  "$schema": "https://schemas.premid.app/metadata/1.0",
  "author": {
    "name": "Xyszx",
    "id": "593774699654283265"
  },
  "url": "blob-project.com",
  "description": {
    "en": "Hello, welcome to Blob Project. We are from Jakarta, Indonesia. We create an amazing project and are trusted by thousands of people.",
    "ga_IE": "Dia duit, Fáilte go dtí an tionscadal. Táimid ó Iacárta, an Indinéis.Cruthaímid tionscadal iontach agus tá muinín acu as na mílte duine."
  },
  "service": "Blob Project",
  "version": "1.0.2",
  "logo": "https://i.imgur.com/xUh0qSN.png",
  "thumbnail": "https://i.imgur.com/zzRmX8Sh.jpg",
  "color": "#7289DA",
  "tags": [
    "coding"
  ],
  "category": "other"
}
